grade50/__init__.py
grade50/main.py
grade50/templates/default.jinja2
grade50-0.4.dist-info/LICENSE
grade50-0.4.dist-info/METADATA
grade50-0.4.dist-info/WHEEL
grade50-0.4.dist-info/entry_points.txt
grade50-0.4.dist-info/top_level.txt
grade50-0.4.dist-info/RECORD
