Metadata-Version: 2.1
Name: grade50
Version: 0.4
Summary: grade student submissions based on check50 json reports.
Home-page: https://github.com/pazz/grade50
Author: Patrick Totzke
Author-email: patricktotzke@gmail.com
License: UNKNOWN
Platform: UNKNOWN
Classifier: Programming Language :: Python :: 3
Classifier: License :: OSI Approved :: MIT License
Classifier: Operating System :: OS Independent
Requires-Python: >=3.6
Requires-Dist: Jinja2 (>=2.10.1)
